{"nodes": [{"id": "lib_screens_free_bells_screen_dart", "label": "free_bells_screen.dart", "file_type": "code", "source_file": "lib/screens/free_bells_screen.dart", "source_location": null}, {"id": "lib_screens_free_bells_screen_dart_freebellsscreen", "label": "FreeBellsScreen", "file_type": "code", "source_file": "lib/screens/free_bells_screen.dart", "source_location": null}, {"id": "lib_screens_free_bells_screen_dart_freebellsscreenstate", "label": "_FreeBellsScreenState", "file_type": "code", "source_file": "lib/screens/free_bells_screen.dart", "source_location": null}, {"id": "lib_screens_free_bells_screen_dart_initstate", "label": "initState", "file_type": "code", "source_file": "lib/screens/free_bells_screen.dart", "source_location": null}, {"id": "lib_screens_free_bells_screen_dart_teachercolor", "label": "_teacherColor", "file_type": "code", "source_file": "lib/screens/free_bells_screen.dart", "source_location": null}, {"id": "lib_screens_free_bells_screen_dart_teachername", "label": "_teacherName", "file_type": "code", "source_file": "lib/screens/free_bells_screen.dart", "source_location": null}, {"id": "lib_screens_free_bells_screen_dart_subject", "label": "_subject", "file_type": "code", "source_file": "lib/screens/free_bells_screen.dart", "source_location": null}, {"id": "lib_screens_free_bells_screen_dart_teacherbyid", "label": "_teacherById", "file_type": "code", "source_file": "lib/screens/free_bells_screen.dart", "source_location": null}, {"id": "lib_screens_free_bells_screen_dart_issubstituted", "label": "_isSubstituted", "file_type": "code", "source_file": "lib/screens/free_bells_screen.dart", "source_location": null}, {"id": "lib_screens_free_bells_screen_dart_text", "label": "Text", "file_type": "code", "source_file": "lib/screens/free_bells_screen.dart", "source_location": null}, {"id": "lib_screens_free_bells_screen_dart_sizedbox", "label": "SizedBox", "file_type": "code", "source_file": "lib/screens/free_bells_screen.dart", "source_location": null}, {"id": "lib_screens_free_bells_screen_dart_divider", "label": "Divider", "file_type": "code", "source_file": "lib/screens/free_bells_screen.dart", "source_location": null}, {"id": "lib_screens_free_bells_screen_dart_padding", "label": "Padding", "file_type": "code", "source_file": "lib/screens/free_bells_screen.dart", "source_location": null}, {"id": "lib_screens_free_bells_screen_dart_flexible", "label": "Flexible", "file_type": "code", "source_file": "lib/screens/free_bells_screen.dart", "source_location": null}, {"id": "lib_screens_free_bells_screen_dart_listtile", "label": "ListTile", "file_type": "code", "source_file": "lib/screens/free_bells_screen.dart", "source_location": null}, {"id": "lib_screens_free_bells_screen_dart_spacer", "label": "Spacer", "file_type": "code", "source_file": "lib/screens/free_bells_screen.dart", "source_location": null}, {"id": "lib_screens_free_bells_screen_dart_build", "label": "build", "file_type": "code", "source_file": "lib/screens/free_bells_screen.dart", "source_location": null}, {"id": "lib_screens_free_bells_screen_dart_scaffold", "label": "Scaffold", "file_type": "code", "source_file": "lib/screens/free_bells_screen.dart", "source_location": null}, {"id": "lib_screens_free_bells_screen_dart_textstyle", "label": "TextStyle", "file_type": "code", "source_file": "lib/screens/free_bells_screen.dart", "source_location": null}, {"id": "lib_screens_free_bells_screen_dart_substitutionhistoryscreen", "label": "SubstitutionHistoryScreen", "file_type": "code", "source_file": "lib/screens/free_bells_screen.dart", "source_location": null}, {"id": "lib_screens_free_bells_screen_dart_buildbellcard", "label": "_buildBellCard", "file_type": "code", "source_file": "lib/screens/free_bells_screen.dart", "source_location": null}, {"id": "lib_screens_free_bells_screen_dart_container", "label": "Container", "file_type": "code", "source_file": "lib/screens/free_bells_screen.dart", "source_location": null}, {"id": "lib_screens_free_bells_screen_dart_buildclassrow", "label": "_buildClassRow", "file_type": "code", "source_file": "lib/screens/free_bells_screen.dart", "source_location": null}, {"id": "lib_screens_free_bells_screen_dart_inkwell", "label": "InkWell", "file_type": "code", "source_file": "lib/screens/free_bells_screen.dart", "source_location": null}, {"id": "lib_screens_free_bells_screen_dart_emptystate", "label": "_emptyState", "file_type": "code", "source_file": "lib/screens/free_bells_screen.dart", "source_location": null}, {"id": "package_flutter_material_dart", "label": "package:flutter/material.dart", "file_type": "code", "source_file": "lib/screens/free_bells_screen.dart", "source_location": null}, {"id": "models_teacher_dart", "label": "../models/teacher.dart", "file_type": "code", "source_file": "lib/screens/free_bells_screen.dart", "source_location": null}, {"id": "models_timetable_entry_dart", "label": "../models/timetable_entry.dart", "file_type": "code", "source_file": "lib/screens/free_bells_screen.dart", "source_location": null}, {"id": "models_substitution_record_dart", "label": "../models/substitution_record.dart", "file_type": "code", "source_file": "lib/screens/free_bells_screen.dart", "source_location": null}, {"id": "services_timetable_service_dart", "label": "../services/timetable_service.dart", "file_type": "code", "source_file": "lib/screens/free_bells_screen.dart", "source_location": null}, {"id": "services_substitution_history_service_dart", "label": "../services/substitution_history_service.dart", "file_type": "code", "source_file": "lib/screens/free_bells_screen.dart", "source_location": null}, {"id": "theme_dart", "label": "../theme.dart", "file_type": "code", "source_file": "lib/screens/free_bells_screen.dart", "source_location": null}, {"id": "substitution_history_screen_dart", "label": "substitution_history_screen.dart", "file_type": "code", "source_file": "lib/screens/free_bells_screen.dart", "source_location": null}], "edges": [{"source": "lib_screens_free_bells_screen_dart", "target": "lib_screens_free_bells_screen_dart_freebellsscreen", "relation": "defines", "confidence": "EXTRACTED", "confidence_score": 1.0, "source_file": "lib/screens/free_bells_screen.dart", "source_location": null, "weight": 1.0}, {"source": "lib_screens_free_bells_screen_dart", "target": "lib_screens_free_bells_screen_dart_freebellsscreenstate", "relation": "defines", "confidence": "EXTRACTED", "confidence_score": 1.0, "source_file": "lib/screens/free_bells_screen.dart", "source_location": null, "weight": 1.0}, {"source": "lib_screens_free_bells_screen_dart", "target": "lib_screens_free_bells_screen_dart_initstate", "relation": "defines", "confidence": "EXTRACTED", "confidence_score": 1.0, "source_file": "lib/screens/free_bells_screen.dart", "source_location": null, "weight": 1.0}, {"source": "lib_screens_free_bells_screen_dart", "target": "lib_screens_free_bells_screen_dart_teachercolor", "relation": "defines", "confidence": "EXTRACTED", "confidence_score": 1.0, "source_file": "lib/screens/free_bells_screen.dart", "source_location": null, "weight": 1.0}, {"source": "lib_screens_free_bells_screen_dart", "target": "lib_screens_free_bells_screen_dart_teachername", "relation": "defines", "confidence": "EXTRACTED", "confidence_score": 1.0, "source_file": "lib/screens/free_bells_screen.dart", "source_location": null, "weight": 1.0}, {"source": "lib_screens_free_bells_screen_dart", "target": "lib_screens_free_bells_screen_dart_subject", "relation": "defines", "confidence": "EXTRACTED", "confidence_score": 1.0, "source_file": "lib/screens/free_bells_screen.dart", "source_location": null, "weight": 1.0}, {"source": "lib_screens_free_bells_screen_dart", "target": "lib_screens_free_bells_screen_dart_teacherbyid", "relation": "defines", "confidence": "EXTRACTED", "confidence_score": 1.0, "source_file": "lib/screens/free_bells_screen.dart", "source_location": null, "weight": 1.0}, {"source": "lib_screens_free_bells_screen_dart", "target": "lib_screens_free_bells_screen_dart_issubstituted", "relation": "defines", "confidence": "EXTRACTED", "confidence_score": 1.0, "source_file": "lib/screens/free_bells_screen.dart", "source_location": null, "weight": 1.0}, {"source": "lib_screens_free_bells_screen_dart", "target": "lib_screens_free_bells_screen_dart_text", "relation": "defines", "confidence": "EXTRACTED", "confidence_score": 1.0, "source_file": "lib/screens/free_bells_screen.dart", "source_location": null, "weight": 1.0}, {"source": "lib_screens_free_bells_screen_dart", "target": "lib_screens_free_bells_screen_dart_sizedbox", "relation": "defines", "confidence": "EXTRACTED", "confidence_score": 1.0, "source_file": "lib/screens/free_bells_screen.dart", "source_location": null, "weight": 1.0}, {"source": "lib_screens_free_bells_screen_dart", "target": "lib_screens_free_bells_screen_dart_divider", "relation": "defines", "confidence": "EXTRACTED", "confidence_score": 1.0, "source_file": "lib/screens/free_bells_screen.dart", "source_location": null, "weight": 1.0}, {"source": "lib_screens_free_bells_screen_dart", "target": "lib_screens_free_bells_screen_dart_padding", "relation": "defines", "confidence": "EXTRACTED", "confidence_score": 1.0, "source_file": "lib/screens/free_bells_screen.dart", "source_location": null, "weight": 1.0}, {"source": "lib_screens_free_bells_screen_dart", "target": "lib_screens_free_bells_screen_dart_flexible", "relation": "defines", "confidence": "EXTRACTED", "confidence_score": 1.0, "source_file": "lib/screens/free_bells_screen.dart", "source_location": null, "weight": 1.0}, {"source": "lib_screens_free_bells_screen_dart", "target": "lib_screens_free_bells_screen_dart_listtile", "relation": "defines", "confidence": "EXTRACTED", "confidence_score": 1.0, "source_file": "lib/screens/free_bells_screen.dart", "source_location": null, "weight": 1.0}, {"source": "lib_screens_free_bells_screen_dart", "target": "lib_screens_free_bells_screen_dart_spacer", "relation": "defines", "confidence": "EXTRACTED", "confidence_score": 1.0, "source_file": "lib/screens/free_bells_screen.dart", "source_location": null, "weight": 1.0}, {"source": "lib_screens_free_bells_screen_dart", "target": "lib_screens_free_bells_screen_dart_build", "relation": "defines", "confidence": "EXTRACTED", "confidence_score": 1.0, "source_file": "lib/screens/free_bells_screen.dart", "source_location": null, "weight": 1.0}, {"source": "lib_screens_free_bells_screen_dart", "target": "lib_screens_free_bells_screen_dart_scaffold", "relation": "defines", "confidence": "EXTRACTED", "confidence_score": 1.0, "source_file": "lib/screens/free_bells_screen.dart", "source_location": null, "weight": 1.0}, {"source": "lib_screens_free_bells_screen_dart", "target": "lib_screens_free_bells_screen_dart_textstyle", "relation": "defines", "confidence": "EXTRACTED", "confidence_score": 1.0, "source_file": "lib/screens/free_bells_screen.dart", "source_location": null, "weight": 1.0}, {"source": "lib_screens_free_bells_screen_dart", "target": "lib_screens_free_bells_screen_dart_substitutionhistoryscreen", "relation": "defines", "confidence": "EXTRACTED", "confidence_score": 1.0, "source_file": "lib/screens/free_bells_screen.dart", "source_location": null, "weight": 1.0}, {"source": "lib_screens_free_bells_screen_dart", "target": "lib_screens_free_bells_screen_dart_buildbellcard", "relation": "defines", "confidence": "EXTRACTED", "confidence_score": 1.0, "source_file": "lib/screens/free_bells_screen.dart", "source_location": null, "weight": 1.0}, {"source": "lib_screens_free_bells_screen_dart", "target": "lib_screens_free_bells_screen_dart_container", "relation": "defines", "confidence": "EXTRACTED", "confidence_score": 1.0, "source_file": "lib/screens/free_bells_screen.dart", "source_location": null, "weight": 1.0}, {"source": "lib_screens_free_bells_screen_dart", "target": "lib_screens_free_bells_screen_dart_buildclassrow", "relation": "defines", "confidence": "EXTRACTED", "confidence_score": 1.0, "source_file": "lib/screens/free_bells_screen.dart", "source_location": null, "weight": 1.0}, {"source": "lib_screens_free_bells_screen_dart", "target": "lib_screens_free_bells_screen_dart_inkwell", "relation": "defines", "confidence": "EXTRACTED", "confidence_score": 1.0, "source_file": "lib/screens/free_bells_screen.dart", "source_location": null, "weight": 1.0}, {"source": "lib_screens_free_bells_screen_dart", "target": "lib_screens_free_bells_screen_dart_emptystate", "relation": "defines", "confidence": "EXTRACTED", "confidence_score": 1.0, "source_file": "lib/screens/free_bells_screen.dart", "source_location": null, "weight": 1.0}, {"source": "lib_screens_free_bells_screen_dart", "target": "package_flutter_material_dart", "relation": "imports", "confidence": "EXTRACTED", "confidence_score": 1.0, "source_file": "lib/screens/free_bells_screen.dart", "source_location": null, "weight": 1.0}, {"source": "lib_screens_free_bells_screen_dart", "target": "models_teacher_dart", "relation": "imports", "confidence": "EXTRACTED", "confidence_score": 1.0, "source_file": "lib/screens/free_bells_screen.dart", "source_location": null, "weight": 1.0}, {"source": "lib_screens_free_bells_screen_dart", "target": "models_timetable_entry_dart", "relation": "imports", "confidence": "EXTRACTED", "confidence_score": 1.0, "source_file": "lib/screens/free_bells_screen.dart", "source_location": null, "weight": 1.0}, {"source": "lib_screens_free_bells_screen_dart", "target": "models_substitution_record_dart", "relation": "imports", "confidence": "EXTRACTED", "confidence_score": 1.0, "source_file": "lib/screens/free_bells_screen.dart", "source_location": null, "weight": 1.0}, {"source": "lib_screens_free_bells_screen_dart", "target": "services_timetable_service_dart", "relation": "imports", "confidence": "EXTRACTED", "confidence_score": 1.0, "source_file": "lib/screens/free_bells_screen.dart", "source_location": null, "weight": 1.0}, {"source": "lib_screens_free_bells_screen_dart", "target": "services_substitution_history_service_dart", "relation": "imports", "confidence": "EXTRACTED", "confidence_score": 1.0, "source_file": "lib/screens/free_bells_screen.dart", "source_location": null, "weight": 1.0}, {"source": "lib_screens_free_bells_screen_dart", "target": "theme_dart", "relation": "imports", "confidence": "EXTRACTED", "confidence_score": 1.0, "source_file": "lib/screens/free_bells_screen.dart", "source_location": null, "weight": 1.0}, {"source": "lib_screens_free_bells_screen_dart", "target": "substitution_history_screen_dart", "relation": "imports", "confidence": "EXTRACTED", "confidence_score": 1.0, "source_file": "lib/screens/free_bells_screen.dart", "source_location": null, "weight": 1.0}]}